{
  "GI": "2019080402,0280,10002,1,20:50:06",
  "TO": {
    "H": {
      "T": "ＤｅＮＡ,DB",
      "O": [
        "1,1700059,8,8,神里,",
        "2,1200053,5,51,宮崎,",
        "3,1700020,9,99,ソト,",
        "4,1000002,7,25,筒香,",
        "5,1300003,3,2,ロペス,",
        "6,1000007,1,65,国吉,",
        "7,600003,6,9,大和,",
        "8,1300093,2,39,嶺井,",
        "9,1500063,4,31,柴田,"
      ]
    },
    "V": {
      "T": "巨人,G",
      "O": [
        "1,500037,9,9,亀井,",
        "2,700003,6,6,坂本勇,",
        "3,800043,8,8,丸,",
        "4,1400101,3,25,岡本,",
        "5,1500047,7,43,重信,",
        "6,1700047,4,60,若林,",
        "7,1500050,5,56,山本,",
        "8,1300029,1,28,田口,",
        "9,1700044,2,46,大城,"
      ]
    }
  },
  "SI": {
    "H": {
      "R": "3,3",
      "S": [
        "1,1",
        "2,0",
        "3,1",
        "4,0",
        "5,0",
        "6,1",
        "7,0"
      ]
    },
    "V": {
      "R": "2,2",
      "S": [
        "1,0",
        "2,1",
        "3,0",
        "4,0",
        "5,0",
        "6,0",
        "7,1",
        "8,0"
      ]
    }
  },
  "St": "横浜,8,2,1300029,1,1,1300003,2,2,3,0,2,3,1,000,,,,,,,",
  "PI": {
    "N": "3",
    "B": [
      "1,1,154,126,4,8,144,1,ファウル,0",
      "2,1,188,96,1,22,147,18,ボール,0",
      "3,4,16,193,9,13,133,18,ボール,0",
      "4,1,73,24,3,15,147,18,ボール,0",
      "5,4,67,80,3,1,131,1,ファウル,0",
      "6,4,144,138,4,8,133,1,ファウル,0",
      "7,1,153,109,4,8,147,1,ファウル,0",
      "8,1,170,70,1,22,147,11,ゴロ,0"
    ]
  },
  "RI": {
    "R": "1,11,ゴロ,4,139,183,,,4-3A",
    "Ps": "4,3,"
  },
  "TR": "32,8,0,34,8,1"
}